invenio_theme_tuw/__init__.py
invenio_theme_tuw/config.py
invenio_theme_tuw/ext.py
invenio_theme_tuw/search.py
invenio_theme_tuw/startup.py
invenio_theme_tuw/utils.py
invenio_theme_tuw/views.py
invenio_theme_tuw/webpack.py
invenio_theme_tuw/community_stats/__init__.py
invenio_theme_tuw/community_stats/data.py
invenio_theme_tuw/community_stats/maps.py
invenio_theme_tuw/community_stats/data/ne_110m_admin_0_countries.zip
invenio_theme_tuw/theme/assets/semantic-ui/js/invenio_theme_tuw/PublishModal.js
invenio_theme_tuw/theme/assets/semantic-ui/js/invenio_theme_tuw/RequestMetadata.js
invenio_theme_tuw/theme/assets/semantic-ui/js/invenio_theme_tuw/UploaderField.js
invenio_theme_tuw/theme/assets/semantic-ui/js/invenio_theme_tuw/theme.js
invenio_theme_tuw/theme/assets/semantic-ui/js/invenio_theme_tuw/clipboard/index.js
invenio_theme_tuw/theme/assets/semantic-ui/js/invenio_theme_tuw/outreach/index.js
invenio_theme_tuw/theme/assets/semantic-ui/js/invenio_theme_tuw/snowfall/index.js
invenio_theme_tuw/theme/assets/semantic-ui/js/invenio_theme_tuw/tracking/index.js
invenio_theme_tuw/theme/assets/semantic-ui/less/invenio_theme_tuw/compose_outreach.less
invenio_theme_tuw/theme/assets/semantic-ui/less/invenio_theme_tuw/login.less
invenio_theme_tuw/theme/assets/semantic-ui/less/invenio_theme_tuw/task_failures.less
invenio_theme_tuw/theme/assets/semantic-ui/less/invenio_theme_tuw/tuwstone.less
invenio_theme_tuw/theme/assets/semantic-ui/less/invenio_theme_tuw/user_infos.less
invenio_theme_tuw/theme/assets/semantic-ui/less/invenio_theme_tuw/users_welcome.less
invenio_theme_tuw/theme/assets/semantic-ui/less/invenio_theme_tuw/theme/theme.less
invenio_theme_tuw/theme/assets/semantic-ui/less/invenio_theme_tuw/theme/collections/breadcrumb.overrides
invenio_theme_tuw/theme/assets/semantic-ui/less/invenio_theme_tuw/theme/collections/breadcrumb.variables
invenio_theme_tuw/theme/assets/semantic-ui/less/invenio_theme_tuw/theme/collections/form.overrides
invenio_theme_tuw-2026.0.1.dist-info/METADATA
invenio_theme_tuw-2026.0.1.dist-info/WHEEL
invenio_theme_tuw-2026.0.1.dist-info/entry_points.txt
invenio_theme_tuw-2026.0.1.dist-info/licenses/AUTHORS.rst
invenio_theme_tuw-2026.0.1.dist-info/licenses/LICENSE
invenio_theme_tuw-2026.0.1.dist-info/RECORD
